justMulti/__init__.py
justMulti/__main__.py
justMulti/_compat.py
justMulti/core.py
justMulti/paragraph.py
justMulti/utils.py
justMulti/stoplists/Afrikaans.txt
justMulti/stoplists/Albanian.txt
justMulti/stoplists/Arabic.txt
justMulti/stoplists/Aragonese.txt
justMulti/stoplists/Armenian.txt
justMulti/stoplists/Aromanian.txt
justMulti/stoplists/Asturian.txt
justMulti/stoplists/Azerbaijani.txt
justMulti/stoplists/Basque.txt
justMulti/stoplists/Belarusian.txt
justMulti/stoplists/Belarusian_Taraskievica.txt
justMulti/stoplists/Bengali.txt
justMulti/stoplists/Bishnupriya_Manipuri.txt
justMulti/stoplists/Bosnian.txt
justMulti/stoplists/Breton.txt
justMulti/stoplists/Bulgarian.txt
justMulti/stoplists/Catalan.txt
justMulti/stoplists/Cebuano.txt
justMulti/stoplists/Chuvash.txt
justMulti/stoplists/Croatian.txt
justMulti/stoplists/Czech.txt
justMulti/stoplists/Danish.txt
justMulti/stoplists/Dutch.txt
justMulti/stoplists/English.txt
justMulti/stoplists/Esperanto.txt
justMulti/stoplists/Estonian.txt
justMulti/stoplists/Finnish.txt
justMulti/stoplists/French.txt
justMulti/stoplists/Galician.txt
justMulti/stoplists/Georgian.txt
justMulti/stoplists/German.txt
justMulti/stoplists/Greek.txt
justMulti/stoplists/Gujarati.txt
justMulti/stoplists/Haitian.txt
justMulti/stoplists/Hebrew.txt
justMulti/stoplists/Hindi.txt
justMulti/stoplists/Hungarian.txt
justMulti/stoplists/Icelandic.txt
justMulti/stoplists/Ido.txt
justMulti/stoplists/Igbo.txt
justMulti/stoplists/Indonesian.txt
justMulti/stoplists/Irish.txt
justMulti/stoplists/Italian.txt
justMulti/stoplists/Javanese.txt
justMulti/stoplists/Kannada.txt
justMulti/stoplists/Kazakh.txt
justMulti/stoplists/Korean.txt
justMulti/stoplists/Kurdish.txt
justMulti/stoplists/Kyrgyz.txt
justMulti/stoplists/Latin.txt
justMulti/stoplists/Latvian.txt
justMulti/stoplists/Lithuanian.txt
justMulti/stoplists/Lombard.txt
justMulti/stoplists/Low_Saxon.txt
justMulti/stoplists/Luxembourgish.txt
justMulti/stoplists/Macedonian.txt
justMulti/stoplists/Malay.txt
justMulti-0.0.3.dist-info/METADATA
justMulti-0.0.3.dist-info/WHEEL
justMulti-0.0.3.dist-info/top_level.txt
justMulti-0.0.3.dist-info/RECORD
