Metadata-Version: 2.1
Name: justMulti
Version: 0.0.3
Summary: Parse html strings
Author: Vrushank Desai
Author-email: <vrushdesai0@gmail.com>
Keywords: html,parsing
Requires-Dist: lxml
